README.md
flask_config.py
setup.py
Flask_Config.egg-info/PKG-INFO
Flask_Config.egg-info/SOURCES.txt
Flask_Config.egg-info/dependency_links.txt
Flask_Config.egg-info/namespace_packages.txt
Flask_Config.egg-info/top_level.txt
Flask_Config.egg-info/zip-safe