Metadata-Version: 1.1
Name: Flask-Config
Version: 0.2.1
Summary: Flask configuration class
Home-page: https://github.com/salsita/flask-config
Author: Salsita Software
Author-email: python@salsitasoft.com
License: MIT
Download-URL: https://github.com/salsita/flask-config/tarball/v0.2.1
Keywords: flask,settings,configuration
Platform: any
Classifier: Development Status :: 4 - Beta
Classifier: Environment :: Web Environment
Classifier: Framework :: Flask
Classifier: Operating System :: OS Independent
Classifier: Intended Audience :: Developers
Classifier: Programming Language :: Python
Classifier: Programming Language :: Python :: 2.6
Classifier: Programming Language :: Python :: 2.7
Classifier: Programming Language :: Python :: 3.3
Classifier: Programming Language :: Python :: 3.4
Classifier: License :: OSI Approved :: MIT License
Classifier: Topic :: Internet :: WWW/HTTP :: Dynamic Content
Classifier: Topic :: Software Development :: Libraries :: Python Modules
